collective.easyformplugin.poll-1.0a1-py2.7-nspkg.pth
collective/easyformplugin/poll/__init__.py
collective/easyformplugin/poll/behaviors.py
collective/easyformplugin/poll/behaviors.zcml
collective/easyformplugin/poll/configure.zcml
collective/easyformplugin/poll/easyform.py
collective/easyformplugin/poll/easyform.zcml
collective/easyformplugin/poll/interfaces.py
collective/easyformplugin/poll/permissions.zcml
collective/easyformplugin/poll/setuphandlers.py
collective/easyformplugin/poll/testing.py
collective/easyformplugin/poll/browser/__init__.py
collective/easyformplugin/poll/browser/configure.zcml
collective/easyformplugin/poll/browser/poll.pt
collective/easyformplugin/poll/browser/pollblock.pt
collective/easyformplugin/poll/browser/saveddata.pt
collective/easyformplugin/poll/browser/view.py
collective/easyformplugin/poll/browser/viewlet.py
collective/easyformplugin/poll/browser/overrides/.gitkeep
collective/easyformplugin/poll/browser/static/.gitkeep
collective/easyformplugin/poll/browser/static/Chart.bundle.min.js
collective/easyformplugin/poll/browser/static/Chart.min.css
collective/easyformplugin/poll/locales/README.rst
collective/easyformplugin/poll/locales/__init__.py
collective/easyformplugin/poll/locales/collective.easyformplugin.poll.pot
collective/easyformplugin/poll/locales/update.py
collective/easyformplugin/poll/locales/update.sh
collective/easyformplugin/poll/locales/en/LC_MESSAGES/collective.easyformplugin.poll.mo
collective/easyformplugin/poll/locales/en/LC_MESSAGES/collective.easyformplugin.poll.po
collective/easyformplugin/poll/profiles/default/actions.xml
collective/easyformplugin/poll/profiles/default/browserlayer.xml
collective/easyformplugin/poll/profiles/default/catalog.xml
collective/easyformplugin/poll/profiles/default/metadata.xml
collective/easyformplugin/poll/profiles/default/registry.xml
collective/easyformplugin/poll/profiles/default/rolemap.xml
collective/easyformplugin/poll/profiles/uninstall/browserlayer.xml
collective.easyformplugin.poll-1.0a1.dist-info/LICENSE.GPL
collective.easyformplugin.poll-1.0a1.dist-info/LICENSE.rst
collective.easyformplugin.poll-1.0a1.dist-info/METADATA
collective.easyformplugin.poll-1.0a1.dist-info/WHEEL
collective.easyformplugin.poll-1.0a1.dist-info/entry_points.txt
collective.easyformplugin.poll-1.0a1.dist-info/namespace_packages.txt
collective.easyformplugin.poll-1.0a1.dist-info/top_level.txt
collective.easyformplugin.poll-1.0a1.dist-info/RECORD
