Metadata-Version: 2.1
Name: collective.easyformplugin.poll
Version: 1.0a1
Summary: Poll support for EasyForm
Home-page: https://github.com/collective/collective.easyformplugin.poll
Author: Oshane Bailey
Author-email: oshane@alteroo.com
License: GPL version 2
Project-URL: Source, https://github.com/collective/collective.easyformplugin.poll
Project-URL: Tracker, https://github.com/collective/collective.easyformplugin.poll/issues
Project-URL: PyPI, https://pypi.python.org/pypi/collective.easyformplugin.poll
Keywords: Python Plone
Platform: UNKNOWN
Classifier: Environment :: Web Environment
Classifier: Framework :: Plone
Classifier: Framework :: Plone :: Addon
Classifier: Framework :: Plone :: 5.0
Classifier: Programming Language :: Python
Classifier: Programming Language :: Python :: 2.7
Classifier: Operating System :: OS Independent
Classifier: License :: OSI Approved :: GNU General Public License v2 (GPLv2)
Requires-Python: ==2.7
Requires-Dist: setuptools
Requires-Dist: z3c.jbot
Requires-Dist: collective.easyform
Requires-Dist: Products.GenericSetup (>=1.8.2)
Requires-Dist: plone.api (>=1.8.4)
Requires-Dist: plone.app.dexterity
Provides-Extra: test
Requires-Dist: plone.app.testing ; extra == 'test'
Requires-Dist: plone.testing (>=5.0.0) ; extra == 'test'
Requires-Dist: plone.app.contenttypes ; extra == 'test'
Requires-Dist: plone.app.robotframework[debug] ; extra == 'test'
